inodeai/__init__.py
inodeai/inodeai.py
inodeai/explainability_interface/__init__.py
inodeai/explainability_interface/dataprocessor.py
inodeai/explainability_interface/explainer.py
inodeai/explainability_interface/factory.py
inodeai/explainability_interface/modelhandler.py
inodeai-0.0.6.dist-info/LICENSE
inodeai-0.0.6.dist-info/METADATA
inodeai-0.0.6.dist-info/WHEEL
inodeai-0.0.6.dist-info/top_level.txt
inodeai-0.0.6.dist-info/RECORD
